Workbook

Sheet Start Here
B2: Contractor Job Cost & Cash Flow Tracker - FREE Edition (3 jobs)
B3: Know which jobs make money before the job is over - not at tax time.
B5: HOW TO USE (10 minutes)
B6: 1. Settings tab: enter your company name, opening cash balance, monthly overhead and start month.
B7: 2. Jobs tab: one row per job - contract value and your estimated cost by category.
B8: 3. Costs Log: every receipt, timesheet or sub invoice - date, job ID, category, amount.
B9: 4. Payments Log: every deposit or progress payment you receive from a client.
B10: 5. Job Dashboard and Cash Flow update automatically. Red = over budget or cash going negative.
B12: COLOR LEGEND
B13: Blue text = a value you type in. Black text = formula, do not overwrite. Green text = pulled from another tab.
B14: Yellow fill = key setting you should review first.
B15: Formula cells are locked so they can't be overwritten by accident. To change a formula: Review > Unprotect Sheet (no password).
... B22: Get it here: [YOUR GUMROAD / LEMON SQUEEZY LINK]

Sheet Settings
A1: Setting | B1: Value | C1: Notes
A2: Company name | B2: Acme Renovations LLC | C2: Shown on dashboards.
A3: Opening cash balance ($) | B3: 15000 | C3: Bank balance on the start month's first day.
A4: Monthly fixed overhead ($) | B4: 1500 | C4: Rent, insurance, truck, software, office salary. Example value - replace.
A5: Target margin after overhead (%) | B5: 0.1 | C5: Jobs projected below this are flagged. Example value - set your own.
A6: Forecast start month | B6: 46023 | C6: Enter the 1st day of a month.

Sheet Jobs
A1: Job ID | B1: Client | C1: Job description | D1: Status | E1: Start date | F1: Contract value ($) | G1: Change orders ($) | H1: Est. labor ($) | I1: Est. materials ($) | J1: Est. subs ($) | K1: Est. equipment ($) | L1: Est. other ($) | M1: Est. total cost ($) | N1: Est. margin (%)
A2: J-101 | B2: Miller | C2: Kitchen remodel | D2: Active | E2: 46027 | F2: 48000 | G2: 2500 | H2: 14000 | I2: 12000 | J2: 6000 | K2: 1200 | L2: 800 | M2: =IF(A2="","",SUM(H2:L2)) -> 34000 | N2: =IF(OR(A2="",F2+G2=0),"",(F2+G2-M2)/(F2+G2)) -> 0.32673267
A3: J-102 | B3: Okafor | C3: Deck + pergola | D3: Complete | E3: 46034 | F3: 22000 | G3: 0 | H3: 6500 | I3: 7000 | J3: 0 | K3: 600 | L3: 400 | M3: =IF(A3="","",SUM(H3:L3)) -> 14500 | N3: =IF(OR(A3="",F3+G3=0),"",(F3+G3-M3)/(F3+G3)) -> 0.34090909
A4: J-103 | B4: Chen | C4: Basement finish | D4: Active | E4: 46055 | F4: 61000 | G4: 0 | H4: 18000 | I4: 14000 | J4: 11000 | K4: 1500 | L4: 1000 | M4: =IF(A4="","",SUM(H4:L4)) -> 45500 | N4: =IF(OR(A4="",F4+G4=0),"",(F4+G4-M4)/(F4+G4)) -> 0.25409836

Sheet Costs Log
A1: Date | B1: Job ID | C1: Category | D1: Vendor / worker | E1: Description | F1: Amount ($)
A2: 46030 | B2: J-101 | C2: Materials | D2: Home Depot | E2: Cabinets deposit | F2: 6200
A3: 46037 | B3: J-101 | C3: Labor | D3: Crew payroll | E3: Week 2 demo + framing | F3: 4100
A4: 46036 | B4: J-102 | C4: Materials | D4: 84 Lumber | E4: Composite decking | F4: 7400
A5: 46043 | B5: J-102 | C5: Labor | D5: Crew payroll | E5: Deck build | F5: 6900
A6: 46056 | B6: J-101 | C6: Subcontractors | D6: Spark Electric | E6: Rough-in electrical | F6: 3800
A7: 46063 | B7: J-103 | C7: Materials | D7: ABC Supply | E7: Drywall + insulation | F7: 5200
A8: 46071 | B8: J-101 | C8: Labor | D8: Crew payroll | E8: Install cabinets | F8: 5600
A9: 46085 | B9: J-103 | C9: Labor | D9: Crew payroll | E9: Framing | F9: 6100

Sheet Payments Log
A1: Date | B1: Job ID | C1: Invoice # | D1: Note | E1: Amount received ($)
A2: 46027 | B2: J-101 | C2: INV-001 | D2: Deposit 30% | E2: 14400
A3: 46034 | B3: J-102 | C3: INV-002 | D3: Deposit 50% | E3: 11000
A4: 46052 | B4: J-102 | C4: INV-003 | D4: Final | E4: 11000
A5: 46055 | B5: J-103 | C5: INV-004 | D5: Deposit 25% | E5: 15250
A6: 46073 | B6: J-101 | C6: INV-005 | D6: Progress 40% | E6: 19200

Sheet Job Dashboard
A1: =Settings!B2&" - Job Dashboard" -> Acme Renovations LLC - Job Dashboard
A3: Job ID | B3: Client | C3: Status | D3: Contract + COs ($) | E3: Est. cost ($) | F3: Actual cost ($) | G3: % of budget used | H3: Received ($) | I3: Profit so far ($) | J3: Margin if job ended now (%) | K3: Flag
A4: =IF(Jobs!A2="","",Jobs!A2) -> J-101 | B4: =IF(A4="","",Jobs!B2) -> Miller | C4: =IF(A4="","",Jobs!D2) -> Active | D4: =IF(A4="","",Jobs!F2+Jobs!G2) -> 50500 | E4: =IF(A4="","",Jobs!M2) -> 34000 | F4: =IF(A4="","",SUMIFS('Costs Log'!$F$2:$F$61,'Costs Log'!$B$2:$B$61,A4)) -> 19700 | G4: =IF(OR(A4="",E4=0),"",F4/E4) -> 0.57941176 | H4: =IF(A4="","",SUMIFS('Payments Log'!$E$2:$E$61,'Payments Log'!$B$2:$B$61,A4)) -> 33600 | I4: =IF(A4="","",H4-F4) -> 13900 | J4: =IF(OR(A4="",D4=0),"",(D4-MAX(E4,F4))/D4) -> 0.32673267 | K4: =IF(A4="","",IF(F4>E4,"OVER BUDGET",IF(J4<Settings!$B$5,"Low margin","OK"))) -> OK
A5: =IF(Jobs!A3="","",Jobs!A3) -> J-102 | B5: =IF(A5="","",Jobs!B3) -> Okafor | C5: =IF(A5="","",Jobs!D3) -> Complete | D5: =IF(A5="","",Jobs!F3+Jobs!G3) -> 22000 | E5: =IF(A5="","",Jobs!M3) -> 14500 | F5: =IF(A5="","",SUMIFS('Costs Log'!$F$2:$F$61,'Costs Log'!$B$2:$B$61,A5)) -> 14300 | G5: =IF(OR(A5="",E5=0),"",F5/E5) -> 0.9862069 | H5: =IF(A5="","",SUMIFS('Payments Log'!$E$2:$E$61,'Payments Log'!$B$2:$B$61,A5)) -> 22000 | I5: =IF(A5="","",H5-F5) -> 7700 | J5: =IF(OR(A5="",D5=0),"",(D5-MAX(E5,F5))/D5) -> 0.34090909 | K5: =IF(A5="","",IF(F5>E5,"OVER BUDGET",IF(J5<Settings!$B$5,"Low margin","OK"))) -> OK
A6: =IF(Jobs!A4="","",Jobs!A4) -> J-103 | B6: =IF(A6="","",Jobs!B4) -> Chen | C6: =IF(A6="","",Jobs!D4) -> Active | D6: =IF(A6="","",Jobs!F4+Jobs!G4) -> 61000 | E6: =IF(A6="","",Jobs!M4) -> 45500 | F6: =IF(A6="","",SUMIFS('Costs Log'!$F$2:$F$61,'Costs Log'!$B$2:$B$61,A6)) -> 11300 | G6: =IF(OR(A6="",E6=0),"",F6/E6) -> 0.24835165 | H6: =IF(A6="","",SUMIFS('Payments Log'!$E$2:$E$61,'Payments Log'!$B$2:$B$61,A6)) -> 15250 | I6: =IF(A6="","",H6-F6) -> 3950 | J6: =IF(OR(A6="",D6=0),"",(D6-MAX(E6,F6))/D6) -> 0.25409836 | K6: =IF(A6="","",IF(F6>E6,"OVER BUDGET",IF(J6<Settings!$B$5,"Low margin","OK"))) -> OK
